README.md
setup.cfg
setup.py
dsnd_probability_tl2024/Binomialdistribution.py
dsnd_probability_tl2024/Gaussiandistribution.py
dsnd_probability_tl2024/Generaldistribution.py
dsnd_probability_tl2024/__init__.py
dsnd_probability_tl2024.egg-info/PKG-INFO
dsnd_probability_tl2024.egg-info/SOURCES.txt
dsnd_probability_tl2024.egg-info/dependency_links.txt
dsnd_probability_tl2024.egg-info/not-zip-safe
dsnd_probability_tl2024.egg-info/top_level.txt