Metadata-Version: 2.1
Name: dsnd-probability-tl2024
Version: 0.5
Summary: Gaussian Binomial distributions
Author: Tony Lockhart
Author-email: Tony.Lockhart@ymail.com
